src/__init__.py
src/roger/__init__.py
src/roger/colors.py
src/roger/key_manager.py
src/roger/roger.py
src/roger/utils.py
roger_cli-0.1.0.dist-info/LICENSE
roger_cli-0.1.0.dist-info/METADATA
roger_cli-0.1.0.dist-info/WHEEL
roger_cli-0.1.0.dist-info/entry_points.txt
roger_cli-0.1.0.dist-info/top_level.txt
roger_cli-0.1.0.dist-info/RECORD
