Metadata-Version: 2.1
Name: roger-cli
Version: 0.1.0
License-File: LICENSE
Requires-Dist: openai (==0.27.4)
Requires-Dist: cryptography (==41.0.1)
